easyml/__init__.py
easyml/data_preprocessing.py
easyml/deployment.py
easyml/models.py
easyml/training.py
easyml/utils.py
test/__init__.py
test/test_data_preprocessing.py
test/test_models.py
test/test_training.py
EasyML_Package-0.1.0.dist-info/LICENSE
EasyML_Package-0.1.0.dist-info/METADATA
EasyML_Package-0.1.0.dist-info/WHEEL
EasyML_Package-0.1.0.dist-info/top_level.txt
EasyML_Package-0.1.0.dist-info/RECORD
