Metadata-Version: 2.2
Name: EasyML-Package
Version: 0.1.0
Summary: A lightweight automated ML pipeline for preprocessing, training, and evaluation.
Home-page: https://github.com/FAbdullah17/EasyML
Author: Fahad Abdullah
Author-email: fahadai.co@gmail.com
Classifier: Programming Language :: Python :: 3
Classifier: License :: OSI Approved :: MIT License
Classifier: Operating System :: OS Independent
Classifier: Topic :: Scientific/Engineering :: Artificial Intelligence
Classifier: Topic :: Software Development :: Libraries
Requires-Python: >=3.8
License-File: LICENSE
Requires-Dist: numpy
Requires-Dist: pandas
Requires-Dist: scikit-learn
Requires-Dist: tensorflow
Requires-Dist: torch
Requires-Dist: transformers
Requires-Dist: xgboost
Requires-Dist: matplotlib
Requires-Dist: seaborn
Requires-Dist: lightgbm
Requires-Dist: catboost
Dynamic: author
Dynamic: author-email
Dynamic: classifier
Dynamic: description
Dynamic: description-content-type
Dynamic: home-page
Dynamic: requires-dist
Dynamic: requires-python
Dynamic: summary
